License.txt
MANIFEST.in
Readme.txt
setup.py
oyevix/__init__.py
oyevix/my_cmd.py
oyevix/vicky.py
oyevix.egg-info/PKG-INFO
oyevix.egg-info/SOURCES.txt
oyevix.egg-info/dependency_links.txt
oyevix.egg-info/top_level.txt