Metadata-Version: 1.0
Name: oyevix
Version: 0.0.1
Summary: This has custom functions.
Home-page: https://github.com/imvickykumar999
Author: Vicky Kumar
Author-email: UNKNOWN
License: MIT
Keywords: custom,python package,function and class
Platform: UNKNOWN
